<?xml version="1.0" encoding="UTF-8" standalone="yes"?>
<OfficeApp
  xmlns="http://schemas.microsoft.com/office/appforoffice/1.1"
  xmlns:xsi="http://www.w3.org/2001/XMLSchema-instance"
  xmlns:bt="http://schemas.microsoft.com/office/officeappbasictypes/1.0"
  xmlns:ov="http://schemas.microsoft.com/office/taskpaneappversionoverrides"
  xsi:type="TaskPaneApp">

  <Id>c2c1d8a4-4d33-4e0d-b4c2-7b6d2f9a8e41</Id>
  <Version>1.0.0.5</Version>
  <ProviderName>WERKHAUS</ProviderName>
  <DefaultLocale>de-DE</DefaultLocale>

  <DisplayName DefaultValue="WERKHAUS Word &amp; Bild"/>
  <Description DefaultValue="WERKHAUS Word &amp; Bild zum Einfügen, Beschriften und Verwalten von Bildern in Word-Dokumenten inklusive Bilddokumentation und Abbildungsverzeichnis."/>

  <IconUrl DefaultValue="https://tool2.wh-sv.de/assets/werkhaus-32.png?v=2"/>
  <HighResolutionIconUrl DefaultValue="https://tool2.wh-sv.de/assets/werkhaus-64.png?v=2"/>
  <SupportUrl DefaultValue="https://tool2.wh-sv.de/support.html"/>

  <AppDomains>
    <AppDomain>https://tool2.wh-sv.de</AppDomain>
  </AppDomains>

  <Hosts>
    <Host Name="Document"/>
  </Hosts>

  <DefaultSettings>
    <SourceLocation DefaultValue="https://tool2.wh-sv.de/taskpane.html"/>
  </DefaultSettings>

  <Permissions>ReadWriteDocument</Permissions>

  <VersionOverrides
    xmlns="http://schemas.microsoft.com/office/taskpaneappversionoverrides"
    xsi:type="VersionOverridesV1_0">
    <Hosts>
      <Host xsi:type="Document">
        <DesktopFormFactor>
          <FunctionFile resid="Commands.Url"/>
          <ExtensionPoint xsi:type="PrimaryCommandSurface">
            <OfficeTab id="TabHome">
              <Group id="Commands.Group">
                <Label resid="Commands.GroupLabel"/>
                <Icon>
                  <bt:Image size="16" resid="Commands.Icon.16"/>
                  <bt:Image size="32" resid="Commands.Icon.32"/>
                  <bt:Image size="80" resid="Commands.Icon.80"/>
                </Icon>
                <Control xsi:type="Button" id="Commands.OpenPane">
                  <Label resid="Commands.ButtonLabel"/>
                  <Supertip>
                    <Title resid="Commands.ButtonLabel"/>
                    <Description resid="Commands.ButtonTooltip"/>
                  </Supertip>
                  <Icon>
                    <bt:Image size="16" resid="Commands.Icon.16"/>
                    <bt:Image size="32" resid="Commands.Icon.32"/>
                    <bt:Image size="80" resid="Commands.Icon.80"/>
                  </Icon>
                  <Action xsi:type="ShowTaskpane">
                    <TaskpaneId>Office.AutoShowTaskpaneWithDocument</TaskpaneId>
                    <SourceLocation resid="Taskpane.Url"/>
                  </Action>
                </Control>
              </Group>
            </OfficeTab>
          </ExtensionPoint>
        </DesktopFormFactor>
      </Host>
    </Hosts>

    <Resources>
      <bt:Images>
        <bt:Image id="Commands.Icon.16" DefaultValue="https://tool2.wh-sv.de/assets/icon-16.png"/>
        <bt:Image id="Commands.Icon.32" DefaultValue="https://tool2.wh-sv.de/assets/icon-32.png"/>
        <bt:Image id="Commands.Icon.80" DefaultValue="https://tool2.wh-sv.de/assets/icon-80 2.png"/>
      </bt:Images>
      <bt:Urls>
        <bt:Url id="Commands.Url" DefaultValue="https://tool2.wh-sv.de/commands.html"/>
        <bt:Url id="Taskpane.Url" DefaultValue="https://tool2.wh-sv.de/taskpane.html"/>
      </bt:Urls>
      <bt:ShortStrings>
        <bt:String id="Commands.GroupLabel" DefaultValue="WERKHAUS Word &amp; Bild"/>
        <bt:String id="Commands.ButtonLabel" DefaultValue="Bild-Tool öffnen"/>
      </bt:ShortStrings>
      <bt:LongStrings>
        <bt:String id="Commands.ButtonTooltip" DefaultValue="Öffnet das WERKHAUS Word &amp; Bild Taskpane."/>
      </bt:LongStrings>
    </Resources>
  </VersionOverrides>
</OfficeApp>
